README.md
setup.py
lockis/__init__.py
lockis/__main__.py
lockis.egg-info/PKG-INFO
lockis.egg-info/SOURCES.txt
lockis.egg-info/dependency_links.txt
lockis.egg-info/requires.txt
lockis.egg-info/top_level.txt