Metadata-Version: 2.1
Name: lockis
Version: 1.0.0
Summary: Encrypt your private data with aes256+hmac
Home-page: https://github.com/mishakorzik/lockis
Author: MishaKorzhik_He1Zen
Author-email: developer.mishakorzhik@gmail.com
License: Apache 2.0
Project-URL: Bug Tracker, https://github.com/mishakorzik/lockis/issues
Project-URL: Donate, https://www.buymeacoffee.com/misakorzik
Keywords: encryption,private,key,cipher,aes256,hmac,ttl,easy,sha256
Classifier: Development Status :: 5 - Production/Stable
Classifier: License :: OSI Approved :: Apache Software License
Classifier: Natural Language :: English
Classifier: Operating System :: OS Independent
Classifier: Programming Language :: Python
Classifier: Programming Language :: Python :: 3
Classifier: Programming Language :: Python :: 3.5
Classifier: Programming Language :: Python :: 3.6
Classifier: Programming Language :: Python :: 3.7
Classifier: Programming Language :: Python :: 3.8
Classifier: Programming Language :: Python :: 3.9
Classifier: Programming Language :: Python :: 3.10
Classifier: Programming Language :: Python :: 3.11
Classifier: Programming Language :: Python :: 3.12
Classifier: Programming Language :: Python :: 3.13
Classifier: Programming Language :: Python :: 3.14
Classifier: Programming Language :: Python :: Implementation :: CPython
Classifier: Programming Language :: Python :: Implementation :: PyPy
Classifier: Topic :: Software Development :: Libraries
Requires-Python: >=3.5
Requires-Dist: cryptography>=3.2
